watchfn/__init__.py
watchfn/client.py
watchfn/models.py
watchfn/adapters/fastapi.py
watchfn/adapters/flask.py
watchfn/alerts/alert_manager.py
watchfn/alerts/conditions.py
watchfn/alerts/channels/slack.py
watchfn/alerts/channels/webhook.py
watchfn/analysis/anomaly_detection.py
watchfn/business/metrics_tracker.py
watchfn/collectors/apm/database_tracer.py
watchfn/collectors/apm/function_profiler.py
watchfn/collectors/errors/breadcrumbs.py
watchfn/collectors/errors/exception_handler.py
watchfn/collectors/infra/process_metrics.py
watchfn/collectors/infra/system_metrics.py
watchfn/core/context_manager.py
watchfn/core/event_router.py
watchfn/core/metric_aggregator.py
watchfn/http/handlers.py
watchfn/http/routes.py
watchfn/storage/database.py
watchfn/storage/memory_storage.py
watchfn/storage/time_series.py
watchfn/trace/context_propagation.py
watchfn/trace/tracer.py
watchfn/utils/batching.py
watchfn-0.0.1.dist-info/METADATA
watchfn-0.0.1.dist-info/WHEEL
watchfn-0.0.1.dist-info/RECORD
