Metadata-Version: 2.4
Name: watchfn
Version: 0.0.1
Summary: Comprehensive self-hosted monitoring and observability platform
Author: 21n
License-Expression: MIT
Requires-Dist: pydantic>=2.6
Requires-Dist: superfunctions>=0.1.0
Provides-Extra: fastapi
Requires-Dist: fastapi; extra == 'fastapi'
Requires-Dist: superfunctions-fastapi>=0.1.0; extra == 'fastapi'
Requires-Dist: uvicorn; extra == 'fastapi'
Provides-Extra: flask
Requires-Dist: flask; extra == 'flask'
Requires-Dist: superfunctions-flask>=0.1.0; extra == 'flask'
